win32more/Windows/Win32/AI/MachineLearning/DirectML/__init__.py
win32more/Windows/Win32/AI/MachineLearning/WinML/__init__.py
win32more/Windows/Win32/Data/HtmlHelp/__init__.py
win32more/Windows/Win32/Data/RightsManagement/__init__.py
win32more/Windows/Win32/Data/Xml/MsXml/__init__.py
win32more/Windows/Win32/Data/Xml/XmlLite/__init__.py
win32more/Windows/Win32/Devices/__init__.py
win32more/Windows/Win32/Devices/AllJoyn/__init__.py
win32more/Windows/Win32/Devices/Beep/__init__.py
win32more/Windows/Win32/Devices/BiometricFramework/__init__.py
win32more/Windows/Win32/Devices/Bluetooth/__init__.py
win32more/Windows/Win32/Devices/Cdrom/__init__.py
win32more/Windows/Win32/Devices/Communication/__init__.py
win32more/Windows/Win32/Devices/DeviceAccess/__init__.py
win32more/Windows/Win32/Devices/DeviceAndDriverInstallation/__init__.py
win32more/Windows/Win32/Devices/DeviceQuery/__init__.py
win32more/Windows/Win32/Devices/Display/__init__.py
win32more/Windows/Win32/Devices/Dvd/__init__.py
win32more/Windows/Win32/Devices/Enumeration/Pnp/__init__.py
win32more/Windows/Win32/Devices/Fax/__init__.py
win32more/Windows/Win32/Devices/FunctionDiscovery/__init__.py
win32more/Windows/Win32/Devices/Geolocation/__init__.py
win32more/Windows/Win32/Devices/HumanInterfaceDevice/__init__.py
win32more/Windows/Win32/Devices/ImageAcquisition/__init__.py
win32more/Windows/Win32/Devices/Nfc/__init__.py
win32more/Windows/Win32/Devices/Nfp/__init__.py
win32more/Windows/Win32/Devices/PortableDevices/__init__.py
win32more/Windows/Win32/Devices/Properties/__init__.py
win32more/Windows/Win32/Devices/Pwm/__init__.py
win32more/Windows/Win32/Devices/Sensors/__init__.py
win32more/Windows/Win32/Devices/SerialCommunication/__init__.py
win32more/Windows/Win32/Devices/Tapi/__init__.py
win32more/Windows/Win32/Devices/Usb/__init__.py
win32more/Windows/Win32/Devices/WebServicesOnDevices/__init__.py
win32more/Windows/Win32/Foundation/__init__.py
win32more/Windows/Win32/Foundation/Metadata/__init__.py
win32more_microsoft_windows_sdk_win32metadata-0.8.68.0.4.dist-info/METADATA
win32more_microsoft_windows_sdk_win32metadata-0.8.68.0.4.dist-info/WHEEL
win32more_microsoft_windows_sdk_win32metadata-0.8.68.0.4.dist-info/RECORD
