Metadata-Version: 2.4
Name: win32more-Microsoft.Windows.SDK.Win32Metadata
Version: 0.8.68.0.4
Requires-Dist: win32more-core==0.8.*
